cdk_cloudformation_tf_aws_keypair/__init__.py
cdk_cloudformation_tf_aws_keypair/py.typed
cdk_cloudformation_tf_aws_keypair/_jsii/__init__.py
cdk_cloudformation_tf_aws_keypair/_jsii/tf-aws-keypair@1.0.0-alpha.7.jsii.tgz
cdk_cloudformation_tf_aws_keypair-1.0.0a7.dist-info/LICENSE
cdk_cloudformation_tf_aws_keypair-1.0.0a7.dist-info/METADATA
cdk_cloudformation_tf_aws_keypair-1.0.0a7.dist-info/WHEEL
cdk_cloudformation_tf_aws_keypair-1.0.0a7.dist-info/top_level.txt
cdk_cloudformation_tf_aws_keypair-1.0.0a7.dist-info/RECORD
